ssh_menu-2.0.5.dist-info/DESCRIPTION.rst
ssh_menu-2.0.5.dist-info/METADATA
ssh_menu-2.0.5.dist-info/RECORD
ssh_menu-2.0.5.dist-info/WHEEL
ssh_menu-2.0.5.dist-info/entry_points.txt
ssh_menu-2.0.5.dist-info/metadata.json
ssh_menu-2.0.5.dist-info/top_level.txt
sshmenu/__init__.py
sshmenu/sshmenu.py
sshmenu/decorators/__init__.py
sshmenu/decorators/decorators.py
sshmenu/tmux/__init__.py
sshmenu/tmux/tmux.py
