Metadata-Version: 2.0
Name: ssh-menu
Version: 2.0.5
Summary: A very simple interactive ssh profile menu
Home-page: https://antonjah.github.io/ssh-menu/
Author: Anton Andersson
Author-email: contact@antonandersson.se
License: UNKNOWN
Download-URL: https://antonjah.github.io/ssh-menu/
Keywords: ssh menu interactive
Platform: UNKNOWN
Classifier: Programming Language :: Python :: 3.6
Requires-Dist: bullet
